sopro/__init__.py
sopro/audio.py
sopro/cli.py
sopro/config.py
sopro/constants.py
sopro/hub.py
sopro/model.py
sopro/sampling.py
sopro/streaming.py
sopro/tokenizer.py
sopro/codec/__init__.py
sopro/codec/mimi.py
sopro/nn/__init__.py
sopro/nn/blocks.py
sopro/nn/embeddings.py
sopro/nn/speaker.py
sopro/nn/xattn.py
sopro-1.0.2.dist-info/licenses/LICENSE.txt
sopro-1.0.2.dist-info/METADATA
sopro-1.0.2.dist-info/WHEEL
sopro-1.0.2.dist-info/entry_points.txt
sopro-1.0.2.dist-info/top_level.txt
sopro-1.0.2.dist-info/RECORD
