Metadata-Version: 2.4
Name: sopro
Version: 1.0.2
Summary: A lightweight text-to-speech model with zero-shot voice cloning.
Author-email: Samuel Vitorino <samvitorino@gmail.com>
License: Apache 2.0
Project-URL: Homepage, https://github.com/samuel-vitorino/sopro
Project-URL: Repository, https://github.com/samuel-vitorino/sopro
Project-URL: Issues, https://github.com/samuel-vitorino/sopro/issues
Requires-Python: >=3.9
License-File: LICENSE.txt
Requires-Dist: numpy>=1.23
Requires-Dist: torch>=2.1
Requires-Dist: transformers>=4.46.0
Requires-Dist: huggingface_hub>=0.23
Requires-Dist: safetensors>=0.4.3
Requires-Dist: sentencepiece>=0.1.99
Requires-Dist: soundfile>=0.12.1
Requires-Dist: torchaudio>=2.1
Requires-Dist: tqdm>=4.66
Dynamic: license-file
